Metadata-Version: 1.0
Name: distribution-calc
Version: 0.1
Summary: Gaussian & Binomial distribution calculations
Home-page: UNKNOWN
Author: Helen Batson
Author-email: helenbatson@gmail.com
License: UNKNOWN
Platform: UNKNOWN
